[
  {
    "photo1": "https://upload.wikimedia.org/wikipedia/fr/thumb/9/9e/PEC_Zwolle_%28logo%29.svg/1200px-PEC_Zwolle_%28logo%29.svg.png",
    "name1": "PEC Zwolle",
    "photo2": "https://encrypted-tbn0.gstatic.com/images?q=tbn:ANd9GcQ1OeyQYM3OwKk9ChdjYhm1g2f1urM_RWuHvw&s",
    "name2": "Willem II",
    "champ": "Pays-Bas. Eredivisie",
    "heure": "19H00",
    "date": "13/12/2024",
    "pro": "Deux équipes vont marquer: OUI"
  },  
  {
    "photo1": "https://upload.wikimedia.org/wikipedia/fr/thumb/a/a2/SC_Freiburg_%28logo%29.svg/640px-SC_Freiburg_%28logo%29.svg.png",
    "name1": "Fribourg",
    "photo2": "https://upload.wikimedia.org/wikipedia/commons/thumb/c/ce/VfL_Wolfsburg_Logo.svg/1200px-VfL_Wolfsburg_Logo.svg.png",
    "name2": "Wolfsbourg",
    "champ": "Allemagne Bundesliga",
    "heure": "19H30",
    "date": "13/12/2024",
    "pro": "1X"
  },
  {
    "photo1": "https://upload.wikimedia.org/wikipedia/fr/thumb/5/58/Toulouse_FC_logo_2021.svg/1200px-Toulouse_FC_logo_2021.svg.png",
    "name1": "Toulouse",
    "photo2": "https://upload.wikimedia.org/wikipedia/en/thumb/2/25/AS_Saint-%C3%89tienne_logo.svg/1200px-AS_Saint-%C3%89tienne_logo.svg.png",
    "name2": "AS Saint-Etienne",
    "champ": "France. Ligue 1",
    "heure": "19H45",
    "date": "13/12/2024",
    "pro": "V1"
  },
    {
    "photo1": "https://encrypted-tbn0.gstatic.com/images?q=tbn:ANd9GcQs6CN8we269tY6L_aeKuhl_IJzqPDd4oi2fw&s",
    "name1": "Empoli",
    "photo2": "https://upload.wikimedia.org/wikipedia/fr/thumb/a/a0/Logo_Torino_FC_2024.svg/1200px-Logo_Torino_FC_2024.svg.png",
    "name2": "Torino",
    "champ": "Italie Série A",
    "heure": "19H45",
    "date": "13/12/2024",
    "pro": "Total: (+1.5)"
  },
  {
    "photo1": "https://upload.wikimedia.org/wikipedia/fr/thumb/c/ca/Logo_Real_Valladolid_CF_1998.svg/1200px-Logo_Real_Valladolid_CF_1998.svg.png",
    "name1": "Real Valladolid",
    "photo2": "https://upload.wikimedia.org/wikipedia/fr/thumb/1/19/Logo_Valencia_CF_2019.svg/1200px-Logo_Valencia_CF_2019.svg.png",
    "name2": "Valencia",
    "champ": "Espagne. LaLiga",
    "heure": "20H00",
    "date": "13/12/2024",
    "pro": "12"
  },
  {
    "photo1": "https://upload.wikimedia.org/wikipedia/fr/thumb/5/57/Logo_Derby_County_2012.svg/1200px-Logo_Derby_County_2012.svg.png",
    "name1": "Derby County",
    "photo2": "https://upload.wikimedia.org/wikipedia/en/thumb/3/38/Portsmouth_FC_logo.svg/1200px-Portsmouth_FC_logo.svg.png",
    "name2": "Portsmouth",
    "champ": "Angleterre. Championship",
    "heure": "20H00",
    "date": "13/12/2024",
    "pro": "Deux équipes vont marquer: OUI"
  },
  {
    "photo1": "https://upload.wikimedia.org/wikipedia/fr/thumb/7/75/Logo_ADO_Den_Haag_2024.svg/1200px-Logo_ADO_Den_Haag_2024.svg.png",
    "name1": "ADO La Haye",
    "photo2": "https://upload.wikimedia.org/wikipedia/en/thumb/6/60/MVV_Maastricht_logo.svg/800px-MVV_Maastricht_logo.svg.png",
    "name2": "MVV Maastricht",
    "champ": "Pays-Bas. Eredivisie",
    "heure": "19H00",
    "date": "13/12/2024",
    "pro": "Deux équipes vont marquer: OUI"
  },
  {
    "photo1": "https://upload.wikimedia.org/wikipedia/fr/thumb/4/46/Logo_AZ_Alkmaar.svg/1200px-Logo_AZ_Alkmaar.svg.png",
    "name1": "Alkmaar",
    "photo2": "https://upload.wikimedia.org/wikipedia/fr/thumb/8/83/FC_Emmen_logo.svg/1200px-FC_Emmen_logo.svg.png",
    "name2": "Emmen",
    "champ": "Pays-Bas. Eredivisie",
    "heure": "19H00",
    "date": "13/12/2024",
    "pro": "2X"
  }
]
